maintainability/api/requirements.txt
maintainability/api/src/__init__.py
maintainability/api/src/config.py
maintainability/api/src/io_operations.py
maintainability/api/src/logger.py
maintainability/api/src/main.py
maintainability/api/src/middleware.py
maintainability/api/src/models.py
maintainability/api/src/router_utils/__init__.py
maintainability/api/src/router_utils/analytics.py
maintainability/api/src/router_utils/extract.py
maintainability/api/src/router_utils/user.py
maintainability/api/src/routers.py
maintainability/api/vercel.json
maintainability/cli/__init__.py
maintainability/cli/main.py
maintainability-0.5.0.dist-info/LICENSE
maintainability-0.5.0.dist-info/METADATA
maintainability-0.5.0.dist-info/WHEEL
maintainability-0.5.0.dist-info/entry_points.txt
maintainability-0.5.0.dist-info/RECORD
