Metadata-Version: 2.1
Name: maintainability
Version: 0.5.0
Summary: Codebase Maintainability Analyzer
License: MIT
Author: voynow
Author-email: voynow99@gmail.com
Requires-Python: >=3.10,<4.0
Classifier: License :: OSI Approved :: MIT License
Classifier: Programming Language :: Python :: 3
Classifier: Programming Language :: Python :: 3.10
Classifier: Programming Language :: Python :: 3.11
Classifier: Programming Language :: Python :: 3.12
